find_kedro/__init__.py
find_kedro/cli.py
find_kedro/core.py
find_kedro-0.1.1.dist-info/LICENSE
find_kedro-0.1.1.dist-info/METADATA
find_kedro-0.1.1.dist-info/WHEEL
find_kedro-0.1.1.dist-info/entry_points.txt
find_kedro-0.1.1.dist-info/top_level.txt
find_kedro-0.1.1.dist-info/RECORD
