Metadata-Version: 2.1
Name: find-kedro
Version: 0.1.1
Summary: finds nodes for your kedro pipeline
Home-page: https://github.com/WaylonWalker/find-kedro.git
Author: Waylon Walker
Author-email: waylon@waylonwalker.com
License: MIT
Platform: UNKNOWN
Classifier: License :: OSI Approved :: MIT License
Classifier: Programming Language :: Python :: 3.6
Classifier: Programming Language :: Python :: 3.7
Requires-Dist: kedro
Requires-Dist: click
Requires-Dist: colorama
Requires-Dist: pygments
